odoo/addons/account_due_list_aging_comment/README.rst
odoo/addons/account_due_list_aging_comment/__init__.py
odoo/addons/account_due_list_aging_comment/__manifest__.py
odoo/addons/account_due_list_aging_comment/i18n/account_due_list_aging_comment.pot
odoo/addons/account_due_list_aging_comment/i18n/de.po
odoo/addons/account_due_list_aging_comment/i18n/es.po
odoo/addons/account_due_list_aging_comment/i18n/it.po
odoo/addons/account_due_list_aging_comment/i18n/pt_BR.po
odoo/addons/account_due_list_aging_comment/i18n/sl.po
odoo/addons/account_due_list_aging_comment/models/__init__.py
odoo/addons/account_due_list_aging_comment/models/account_move_line.py
odoo/addons/account_due_list_aging_comment/static/description/icon.png
odoo/addons/account_due_list_aging_comment/views/payment_view.xml
odoo11_addon_account_due_list_aging_comment-11.0.1.0.0.99.dev2.dist-info/METADATA
odoo11_addon_account_due_list_aging_comment-11.0.1.0.0.99.dev2.dist-info/RECORD
odoo11_addon_account_due_list_aging_comment-11.0.1.0.0.99.dev2.dist-info/WHEEL
odoo11_addon_account_due_list_aging_comment-11.0.1.0.0.99.dev2.dist-info/top_level.txt
